otlet/__init__.py
otlet/__main__.py
otlet/api.py
otlet/api.pyi
otlet/exceptions.py
otlet/markers.py
otlet/packaging/__init__.py
otlet/packaging/version/__init__.py
otlet/packaging/version/_structures.py
otlet/packaging/version/py.typed
otlet/util.py
otlet-1.0.0.post1.dist-info/LICENSE.MIT
otlet-1.0.0.post1.dist-info/LICENSE.APACHE
otlet-1.0.0.post1.dist-info/LICENSE
otlet-1.0.0.post1.dist-info/LICENSE.BSD
otlet-1.0.0.post1.dist-info/WHEEL
otlet-1.0.0.post1.dist-info/METADATA
otlet-1.0.0.post1.dist-info/RECORD
