Metadata-Version: 2.1
Name: otlet
Version: 1.0.0.post1
Summary: Zero-dependency, pure-python wrapper for the PyPI JSON Web API
Home-page: https://github.com/nhtnr/otlet
License: MIT
Author: Noah Tanner (nhtnr)
Author-email: noahtnr@gmail.com
Requires-Python: >=3.6.2,<4.0.0
Classifier: Development Status :: 5 - Production/Stable
Classifier: Intended Audience :: Developers
Classifier: License :: OSI Approved :: Apache Software License
Classifier: License :: OSI Approved :: BSD License
Classifier: License :: OSI Approved :: MIT License
Classifier: Programming Language :: Python :: 3
Classifier: Programming Language :: Python :: 3 :: Only
Classifier: Programming Language :: Python :: 3.10
Classifier: Programming Language :: Python :: 3.7
Classifier: Programming Language :: Python :: 3.8
Classifier: Programming Language :: Python :: 3.9
Provides-Extra: cli
Provides-Extra: docs
Requires-Dist: Sphinx (>=4.5.0,<5.0.0); extra == "docs"
Requires-Dist: otlet-cli (>=1.0.0,<2.0.0); (python_version >= "3.7" and python_version < "4.0") and (extra == "cli")
Requires-Dist: sphinx-rtd-theme (>=1.0.0,<2.0.0); extra == "docs"
Project-URL: Documentation, https://otlet.readthedocs.io/en/latest/
Project-URL: Repository, https://github.com/nhtnr/otlet
